nomad_media_pip/requirements.txt
nomad_media_pip/src/admin/asset_upload/cancel_upload.py
nomad_media_pip/src/admin/asset_upload/multi_thread_upload.py
nomad_media_pip/src/admin/asset_upload/start_asset_upload.py
nomad_media_pip/src/admin/asset_upload/start_related_asset_upload.py
nomad_media_pip/src/admin/asset_upload/upload_asset_part.py
nomad_media_pip/src/admin/asset_upload/upload_asset_part_complete.py
nomad_media_pip/src/admin/asset_upload/upload_complete_asset.py
nomad_media_pip/src/admin/asset_upload/upload_thread.py
nomad_media_pip/src/admin/audit/get_audit.py
nomad_media_pip/src/admin/config/clear_server_cache.py
nomad_media_pip/src/admin/config/get_config.py
nomad_media_pip/src/admin/config/get_server_time.py
nomad_media_pip/src/admin/content/create_content.py
nomad_media_pip/src/admin/content/deactivate_content_user_track.py
nomad_media_pip/src/admin/content/delete_content.py
nomad_media_pip/src/admin/content/get_content.py
nomad_media_pip/src/admin/content/get_content_user_track.py
nomad_media_pip/src/admin/content/get_content_user_track_touch.py
nomad_media_pip/src/admin/content/update_content.py
nomad_media_pip/src/admin/content_definition/create_content_definition.py
nomad_media_pip/src/admin/content_definition/get_content_definition.py
nomad_media_pip/src/admin/content_definition/get_content_definition_groups.py
nomad_media_pip/src/admin/content_definition/get_content_definition_types.py
nomad_media_pip/src/admin/content_definition/get_content_definitions.py
nomad_media_pip/src/admin/content_definition/get_system_roles.py
nomad_media_pip/src/admin/content_definition/update_content_definition.py
nomad_media_pip/src/admin/event/add_live_schedule_to_event.py
nomad_media_pip/src/admin/event/create_update_event.py
nomad_media_pip/src/admin/event/delete_event.py
nomad_media_pip/src/admin/event/extend_live_schedule.py
nomad_media_pip/src/admin/event/get_live_schedule.py
nomad_media_pip/src/admin/event/start_live_schedule.py
nomad_media_pip-0.1.8.dist-info/METADATA
nomad_media_pip-0.1.8.dist-info/WHEEL
nomad_media_pip-0.1.8.dist-info/RECORD
