Metadata-Version: 2.4
Name: nomad_media_pip
Version: 0.1.8
Summary: Nomad Media SDK PIP
Author: Nomad Media
Requires-Python: >=3.12
Classifier: Programming Language :: Python :: 3
Classifier: Programming Language :: Python :: 3.12
Classifier: Programming Language :: Python :: 3.13
Classifier: Programming Language :: Python :: 3.14
Requires-Dist: deepdiff
Requires-Dist: requests
